qdyhgq_music_mcp_demo/__init__.py
qdyhgq_music_mcp_demo-0.1.1.dist-info/METADATA
qdyhgq_music_mcp_demo-0.1.1.dist-info/WHEEL
qdyhgq_music_mcp_demo-0.1.1.dist-info/entry_points.txt
qdyhgq_music_mcp_demo-0.1.1.dist-info/RECORD
